dask_cuml/__init__.py
dask_cuml/_version.py
dask_cuml/core.py
dask_cuml/linear_model/__init__.py
dask_cuml/linear_model/linear_regression.py
dask_cuml/neighbors/__init__.py
dask_cuml/neighbors/nearest_neighbors.py
dask_cuml/tests/__init__.py
dask_cuml/tests/test_linear_regression.py
dask_cuml/tests/test_nearest_neighbors.py
dask_cuml-0.6.0.dist-info/LICENSE
dask_cuml-0.6.0.dist-info/METADATA
dask_cuml-0.6.0.dist-info/WHEEL
dask_cuml-0.6.0.dist-info/top_level.txt
dask_cuml-0.6.0.dist-info/RECORD
