Metadata-Version: 2.1
Name: dask-cuml
Version: 0.6.0
Summary: Distributed ML algorithms on GPUs using Dask
Home-page: https://github.com/rapidsai/dask-cuml
Author: NVIDIA Corporation
Author-email: UNKNOWN
License: Apache Software License 2.0
Platform: UNKNOWN
Classifier: Intended Audience :: Developers
Classifier: Programming Language :: Python
Classifier: Programming Language :: Python :: 3.6
Classifier: Programming Language :: Python :: 3.7
Requires-Dist: numpy
